Workbook

Sheet Dashboard
A1: RETAIL SALES DASHBOARD
A4: TOTAL SALES | D4: TOTAL PROFIT | G4: TOTAL ORDERS | J4: QUANTITY SOLD
A5: =SUM(Data!L2:L152) | D5: =SUM(Data!N2:N152) | G5: =COUNTA(Data!A2:A152) | J5: =SUM(Data!I2:I152)
A9: CATEGORY | B9: TOTAL SALES | D9: SALES STATUS | E9: ORDERS | G9: CATEGORY-WISE SUMMARY
A10: Accessories | B10: =SUMIF(Data!$E$2:$E$152,A10,Data!$L$2:$L$152) | D10: High Sales | E10: =COUNTIF(Data!$P$2:$P$152,D10) | G10: Category | H10: Sales | I10: Profit | J10: Orders | K10: Quantity
A11: Electronics | B11: =SUMIF(Data!$E$2:$E$152,A11,Data!$L$2:$L$152) | D11: Low Sales | E11: =COUNTIF(Data!$P$2:$P$152,D11) | G11: Accessories | H11: =SUMIF(Data!$E$2:$E$152,G11,Data!$L$2:$L$152) | I11: =SUMIF(Data!$E$2:$E$152,G11,Data!$N$2:$N$152) | J11: =COUNTIF(Data!$E$2:$E$152,G11) | K11: =SUMIF(Data!$E$2:$E$152,G11,Data!$I$2:$I$152)
A12: Home | B12: =SUMIF(Data!$E$2:$E$152,A12,Data!$L$2:$L$152) | G12: Electronics | H12: =SUMIF(Data!$E$2:$E$152,G12,Data!$L$2:$L$152) | I12: =SUMIF(Data!$E$2:$E$152,G12,Data!$N$2:$N$152) | J12: =COUNTIF(Data!$E$2:$E$152,G12) | K12: =SUMIF(Data!$E$2:$E$152,G12,Data!$I$2:$I$152)
A13: Stationery | B13: =SUMIF(Data!$E$2:$E$152,A13,Data!$L$2:$L$152) | G13: Home | H13: =SUMIF(Data!$E$2:$E$152,G13,Data!$L$2:$L$152) | I13: =SUMIF(Data!$E$2:$E$152,G13,Data!$N$2:$N$152) | J13: =COUNTIF(Data!$E$2:$E$152,G13) | K13: =SUMIF(Data!$E$2:$E$152,G13,Data!$I$2:$I$152)
G14: Stationery | H14: =SUMIF(Data!$E$2:$E$152,G14,Data!$L$2:$L$152) | I14: =SUMIF(Data!$E$2:$E$152,G14,Data!$N$2:$N$152) | J14: =COUNTIF(Data!$E$2:$E$152,G14) | K14: =SUMIF(Data!$E$2:$E$152,G14,Data!$I$2:$I$152)
A29: Dashboard includes sales/profit/order KPIs, category sales chart, sales-status chart and category summary.
A33: Dashboard includes sales/profit/order KPIs, category sales chart, sales-status chart and category summary.

Sheet README & Explanation
A1: README & DASHBOARD EXPLANATION
A4: 1. Project Overview
A5: Retail Sales Dashboard summarises order data using key performance indicators, category sales and sales-status charts.
A7: 2. Dashboard KPIs
A8: Total Sales = sum of Total_Sales; Total Profit = sum of Profit; Total Orders = count of Order_ID; Quantity Sold = sum of Quantity.
A10: 3. Charts
A11: Sales by Category compares total sales for each product category. High vs Low Sales Orders compares the number of orders in each sales-status group.
A13: 4. Category Summary
A14: The table shows each category's total sales, total profit, order count and quantity sold.
A16: 5. Data Sheet
A17: The Data sheet contains the source order-level data. It is kept separate from the dashboard to make the dashboard clean and easy to read.
A19: 6. How to Use
... A26: Chart values and KPI results are based on the workbook's dataset. Formula results may update when opened in Excel or LibreOffice.

Sheet Data
A1: Order_ID | B1: Order_Date | C1: Product_ID | D1: Product_Name | E1: Category | F1: Region | G1: Sales_Rep | H1: Customer_Type | I1: Quantity | J1: Unit_Price | K1: Discount | L1: Total_Sales | M1: Unit_Cost | N1: Profit | O1: Payment_Method | P1: Sales status
A2: ORD0065 | B2: 46028 | C2: P003 | D2: Water Bottle | E2: Accessories | F2: North | G2: Diya | H2: Member | I2: 4 | J2: 180 | K2: 0.05 | L2: 684 | M2: 127.09 | N2: 175.64 | O2: Cash | P2: Low Sales
A3: ORD0147 | B3: 46031 | C3: P003 | D3: Water Bottle | E3: Accessories | F3: North | G3: Kabir | H3: New | I3: 6 | J3: 180 | K3: 0.15 | L3: 918 | M3: 137.97 | N3: 90.18 | O3: Cash | P3: Low Sales
A4: ORD0032 | B4: 46037 | C4: P004 | D4: Backpack | E4: Accessories | F4: South | G4: Diya | H4: Member | I4: 5 | J4: 750 | K4: 0 | L4: 3750 | M4: 472.9 | N4: 1385.5 | O4: Card | P4: High Sales
A5: ORD0141 | B5: 46040 | C5: P002 | D5: Pen Pack | E5: Stationery | F5: East | G5: Rohan | H5: Regular | I5: 8 | J5: 40 | K5: 0.15 | L5: 272 | M5: 23.33 | N5: 85.36 | O5: Cash | P5: Low Sales
A6: ORD0022 | B6: 46044 | C6: P004 | D6: Backpack | E6: Accessories | F6: North | G6: Kabir | H6: Member | I6: 5 | J6: 750 | K6: 0.1 | L6: 3375 | M6: 458.38 | N6: 1083.1 | O6: UPI | P6: High Sales
A7: ORD0026 | B7: 46044 | C7: P001 | D7: Notebook | E7: Stationery | F7: East | G7: Meera | H7: New | I7: 1 | J7: 60 | K7: 0.15 | L7: 51 | M7: 36.71 | N7: 14.29 | O7: Cash | P7: Low Sales
A8: ORD0081 | B8: 46047 | C8: P005 | D8: USB Drive | E8: Electronics | F8: West | G8: Aarav | H8: Regular | I8: 3 | J8: 450 | K8: 0.15 | L8: 1147.5 | M8: 262.9 | N8: 358.8 | O8: UPI | P8: Low Sales
A9: ORD0117 | B9: 46049 | C9: P001 | D9: Notebook | E9: Stationery | F9: East | G9: Rohan | H9: Member | I9: 3 | J9: 60 | K9: 0.05 | L9: 171 | M9: 38.01 | N9: 56.97 | O9: Card | P9: Low Sales
A10: ORD0060 | B10: 46052 | C10: P004 | D10: Backpack | E10: Accessories | F10: East | G10: Aarav | H10: Regular | I10: 3 | J10: 750 | K10: 0.1 | L10: 2025 | M10: 461.71 | N10: 639.87 | O10: Card | P10: High Sales
A11: ORD0099 | B11: 46055 | C11: P002 | D11: Pen Pack | E11: Stationery | F11: North | G11: Aarav | H11: Member | I11: 2 | J11: 40 | K11: 0.1 | L11: 72 | M11: 24.03 | N11: 23.94 | O11: Card | P11: Low Sales
A12: ORD0134 | B12: 46057 | C12: P005 | D12: USB Drive | E12: Electronics | F12: East | G12: Kabir | H12: New | I12: 8 | J12: 450 | K12: 0.05 | L12: 3420 | M12: 284.48 | N12: 1144.16 | O12: Cash | P12: High Sales
A13: ORD0113 | B13: 46058 | C13: P001 | D13: Notebook | E13: Stationery | F13: East | G13: Meera | H13: New | I13: 2 | J13: 60 | K13: 0.1 | L13: 108 | M13: 42.96 | N13: 22.08 | O13: UPI | P13: Low Sales
... A151: ORD0094 | B151: 46308 | C151: P003 | D151: Water Bottle | E151: Accessories | F151: South | G151: Meera | H151: Member | I151: 7 | J151: 180 | K151: 0.1 | L151: 1134 | M151: 110.78 | N151: 358.54 | O151: Card | P151: Low Sales
